collective.contact.core-1.37-py2.7-nspkg.pth
collective/contact/core/__init__.py
collective/contact/core/adapters.py
collective/contact/core/behaviors.py
collective/contact/core/behaviors.zcml
collective/contact/core/configure.zcml
collective/contact/core/fields.py
collective/contact/core/fti.py
collective/contact/core/indexers.py
collective/contact/core/interfaces.py
collective/contact/core/schema.py
collective/contact/core/setuphandlers.py
collective/contact/core/skins.zcml
collective/contact/core/subscribers.py
collective/contact/core/testing.py
collective/contact/core/testing.zcml
collective/contact/core/utils.py
collective/contact/core/vocabulary.py
collective/contact/core/browser/__init__.py
collective/contact/core/browser/addcontact.py
collective/contact/core/browser/address.py
collective/contact/core/browser/configure.zcml
collective/contact/core/browser/contact.py
collective/contact/core/browser/contactable.py
collective/contact/core/browser/directory.py
collective/contact/core/browser/excelexport.py
collective/contact/core/browser/excelexport.zcml
collective/contact/core/browser/organization.py
collective/contact/core/browser/person.py
collective/contact/core/browser/person_title_mapping.py
collective/contact/core/browser/position.py
collective/contact/core/browser/ttwfields.py
collective/contact/core/browser/utils.py
collective/contact/core/browser/vcard_export.py
collective/contact/core/browser/basefields/__init__.py
collective/contact/core/browser/basefields/views.py
collective/contact/core/browser/basefields/templates/held_position.pt
collective/contact/core/browser/basefields/templates/organization.pt
collective/contact/core/browser/basefields/templates/person.pt
collective/contact/core/browser/basefields/templates/position.pt
collective/contact/core/browser/static/forms.js
collective/contact/core/browser/templates/address.pt
collective/contact/core/browser/templates/contact.pt
collective.contact.core-1.37.dist-info/DESCRIPTION.rst
collective.contact.core-1.37.dist-info/METADATA
collective.contact.core-1.37.dist-info/RECORD
collective.contact.core-1.37.dist-info/WHEEL
collective.contact.core-1.37.dist-info/entry_points.txt
collective.contact.core-1.37.dist-info/metadata.json
collective.contact.core-1.37.dist-info/namespace_packages.txt
collective.contact.core-1.37.dist-info/top_level.txt
