Metadata-Version: 2.0
Name: collective.contact.core
Version: 1.37
Summary: Core package for collective.contact add-ons
Home-page: https://github.com/collective/collective.contact.core
Author: "Cedric Messiant"
Author-email: cedricmessiant@ecreall.com
License: gpl
Download-URL: https://pypi.org/project/collective.contact.core
Keywords: plone contact management organization person position
Platform: UNKNOWN
Classifier: Development Status :: 5 - Production/Stable
Classifier: Environment :: Web Environment
Classifier: Framework :: Plone
Classifier: Framework :: Plone :: 4.2
Classifier: Framework :: Plone :: 4.3
Classifier: Framework :: Plone :: Addon
Classifier: License :: OSI Approved :: GNU General Public License v2 (GPLv2)
Classifier: Operating System :: OS Independent
Classifier: Programming Language :: Python
Classifier: Programming Language :: Python :: 2
Classifier: Programming Language :: Python :: 2.7
Classifier: Topic :: Software Development :: Libraries :: Python Modules
Provides-Extra: test
Requires-Dist: ExtensionClass
Requires-Dist: collective.z3cform.datagridfield
Requires-Dist: collective.contact.widget (>=1.12)
Requires-Dist: collective.dexteritytextindexer
Requires-Dist: setuptools
Requires-Dist: ecreall.helpers.upgrade (>=1.1.6.dev0)
Requires-Dist: five.grok
Requires-Dist: five.globalrequest
Requires-Dist: plone.api (>=1.4.11)
Requires-Dist: plone.app.dexterity
Requires-Dist: plone.app.linkintegrity
Requires-Dist: plone.app.relationfield
Requires-Dist: plone.app.textfield (!=1.2.8)
Requires-Dist: plone.autoform
Requires-Dist: plone.formwidget.datetime
Requires-Dist: plone.formwidget.masterselect (<2.0.0,>=1.3)
Requires-Dist: plone.supermodel
Requires-Dist: Products.CMFPlone
Requires-Dist: vobject
Requires-Dist: zope.schema (>=4.2.1)
Provides-Extra: test
Requires-Dist: plone.app.testing; extra == 'test'
Requires-Dist: plone.app.robotframework; extra == 'test'
Requires-Dist: ecreall.helpers.testing; extra == 'test'
